<?xml version="1.0" encoding="UTF-8"?>
<databaseChangeLog xmlns="http://www.liquibase.org/xml/ns/dbchangelog" xmlns:xsi="http://www.w3.org/2001/XMLSchema-instance"
                   xsi:schemaLocation="http://www.liquibase.org/xml/ns/dbchangelog http://www.liquibase.org/xml/ns/dbchangelog/dbchangelog-3.0.xsd">
    <changeSet id="1.0.0-012" author="euromillions-predictor">
        <insert tableName="draws"><column name="id" value="111"></column><column name="date" value="2006-03-24"></column><column name="cost" value="1.50"></column><column name="stars_count" value="9"></column><column name="numbers_count" value="50"></column></insert>
        <insert tableName="draws_stars"><column name="draw_id" value="111"></column><column name="star" value="4"></column></insert>
        <insert tableName="draws_stars"><column name="draw_id" value="111"></column><column name="star" value="9"></column></insert>
        <insert tableName="draws_numbers"><column name="draw_id" value="111"></column><column name="number" value="17"></column></insert>
        <insert tableName="draws_numbers"><column name="draw_id" value="111"></column><column name="number" value="28"></column></insert>
        <insert tableName="draws_numbers"><column name="draw_id" value="111"></column><column name="number" value="33"></column></insert>
        <insert tableName="draws_numbers"><column name="draw_id" value="111"></column><column name="number" value="35"></column></insert>
        <insert tableName="draws_numbers"><column name="draw_id" value="111"></column><column name="number" value="47"></column></insert>
        <insert tableName="draws_prizes"><column name="draw_id" value="111"></column><column name="stars" value="2"></column><column name="numbers" value="5"></column><column name="prize" value="45191782.00"></column></insert>
        <insert tableName="draws_prizes"><column name="draw_id" value="111"></column><column name="stars" value="1"></column><column name="numbers" value="5"></column><column name="prize" value="242648.50"></column></insert>
        <insert tableName="draws_prizes"><column name="draw_id" value="111"></column><column name="stars" value="0"></column><column name="numbers" value="5"></column><column name="prize" value="151400.00"></column></insert>
        <insert tableName="draws_prizes"><column name="draw_id" value="111"></column><column name="stars" value="2"></column><column name="numbers" value="4"></column><column name="prize" value="4624.20"></column></insert>
        <insert tableName="draws_prizes"><column name="draw_id" value="111"></column><column name="stars" value="1"></column><column name="numbers" value="4"></column><column name="prize" value="225.40"></column></insert>
        <insert tableName="draws_prizes"><column name="draw_id" value="111"></column><column name="stars" value="0"></column><column name="numbers" value="4"></column><column name="prize" value="95.10"></column></insert>
        <insert tableName="draws_prizes"><column name="draw_id" value="111"></column><column name="stars" value="2"></column><column name="numbers" value="3"></column><column name="prize" value="66.80"></column></insert>
        <insert tableName="draws_prizes"><column name="draw_id" value="111"></column><column name="stars" value="1"></column><column name="numbers" value="3"></column><column name="prize" value="24.10"></column></insert>
        <insert tableName="draws_prizes"><column name="draw_id" value="111"></column><column name="stars" value="2"></column><column name="numbers" value="2"></column><column name="prize" value="20.00"></column></insert>
        <insert tableName="draws_prizes"><column name="draw_id" value="111"></column><column name="stars" value="0"></column><column name="numbers" value="3"></column><column name="prize" value="13.50"></column></insert>
        <insert tableName="draws_prizes"><column name="draw_id" value="111"></column><column name="stars" value="2"></column><column name="numbers" value="1"></column><column name="prize" value="8.50"></column></insert>
        <insert tableName="draws_prizes"><column name="draw_id" value="111"></column><column name="stars" value="1"></column><column name="numbers" value="2"></column><column name="prize" value="7.70"></column></insert>

        <insert tableName="draws"><column name="id" value="112"></column><column name="date" value="2006-03-31"></column><column name="cost" value="1.50"></column><column name="stars_count" value="9"></column><column name="numbers_count" value="50"></column></insert>
        <insert tableName="draws_stars"><column name="draw_id" value="112"></column><column name="star" value="6"></column></insert>
        <insert tableName="draws_stars"><column name="draw_id" value="112"></column><column name="star" value="7"></column></insert>
        <insert tableName="draws_numbers"><column name="draw_id" value="112"></column><column name="number" value="3"></column></insert>
        <insert tableName="draws_numbers"><column name="draw_id" value="112"></column><column name="number" value="20"></column></insert>
        <insert tableName="draws_numbers"><column name="draw_id" value="112"></column><column name="number" value="31"></column></insert>
        <insert tableName="draws_numbers"><column name="draw_id" value="112"></column><column name="number" value="45"></column></insert>
        <insert tableName="draws_numbers"><column name="draw_id" value="112"></column><column name="number" value="50"></column></insert>
        <insert tableName="draws_prizes"><column name="draw_id" value="112"></column><column name="stars" value="2"></column><column name="numbers" value="5"></column><column name="prize" value="53102939.00"></column></insert>
        <insert tableName="draws_prizes"><column name="draw_id" value="112"></column><column name="stars" value="1"></column><column name="numbers" value="5"></column><column name="prize" value="551594.10"></column></insert>
        <insert tableName="draws_prizes"><column name="draw_id" value="112"></column><column name="stars" value="0"></column><column name="numbers" value="5"></column><column name="prize" value="71151.50"></column></insert>
        <insert tableName="draws_prizes"><column name="draw_id" value="112"></column><column name="stars" value="2"></column><column name="numbers" value="4"></column><column name="prize" value="5704.50"></column></insert>
        <insert tableName="draws_prizes"><column name="draw_id" value="112"></column><column name="stars" value="1"></column><column name="numbers" value="4"></column><column name="prize" value="193.40"></column></insert>
        <insert tableName="draws_prizes"><column name="draw_id" value="112"></column><column name="stars" value="0"></column><column name="numbers" value="4"></column><column name="prize" value="90.80"></column></insert>
        <insert tableName="draws_prizes"><column name="draw_id" value="112"></column><column name="stars" value="2"></column><column name="numbers" value="3"></column><column name="prize" value="78.10"></column></insert>
        <insert tableName="draws_prizes"><column name="draw_id" value="112"></column><column name="stars" value="1"></column><column name="numbers" value="3"></column><column name="prize" value="22.70"></column></insert>
        <insert tableName="draws_prizes"><column name="draw_id" value="112"></column><column name="stars" value="2"></column><column name="numbers" value="2"></column><column name="prize" value="23.20"></column></insert>
        <insert tableName="draws_prizes"><column name="draw_id" value="112"></column><column name="stars" value="0"></column><column name="numbers" value="3"></column><column name="prize" value="13.80"></column></insert>
        <insert tableName="draws_prizes"><column name="draw_id" value="112"></column><column name="stars" value="2"></column><column name="numbers" value="1"></column><column name="prize" value="9.80"></column></insert>
        <insert tableName="draws_prizes"><column name="draw_id" value="112"></column><column name="stars" value="1"></column><column name="numbers" value="2"></column><column name="prize" value="7.20"></column></insert>

        <insert tableName="draws"><column name="id" value="113"></column><column name="date" value="2006-04-07"></column><column name="cost" value="1.50"></column><column name="stars_count" value="9"></column><column name="numbers_count" value="50"></column></insert>
        <insert tableName="draws_stars"><column name="draw_id" value="113"></column><column name="star" value="4"></column></insert>
        <insert tableName="draws_stars"><column name="draw_id" value="113"></column><column name="star" value="5"></column></insert>
        <insert tableName="draws_numbers"><column name="draw_id" value="113"></column><column name="number" value="12"></column></insert>
        <insert tableName="draws_numbers"><column name="draw_id" value="113"></column><column name="number" value="13"></column></insert>
        <insert tableName="draws_numbers"><column name="draw_id" value="113"></column><column name="number" value="29"></column></insert>
        <insert tableName="draws_numbers"><column name="draw_id" value="113"></column><column name="number" value="44"></column></insert>
        <insert tableName="draws_numbers"><column name="draw_id" value="113"></column><column name="number" value="50"></column></insert>
        <insert tableName="draws_prizes"><column name="draw_id" value="113"></column><column name="stars" value="2"></column><column name="numbers" value="5"></column><column name="prize" value="10485000.00"></column></insert>
        <insert tableName="draws_prizes"><column name="draw_id" value="113"></column><column name="stars" value="1"></column><column name="numbers" value="5"></column><column name="prize" value="719300.00"></column></insert>
        <insert tableName="draws_prizes"><column name="draw_id" value="113"></column><column name="stars" value="0"></column><column name="numbers" value="5"></column><column name="prize" value="43743.40"></column></insert>
        <insert tableName="draws_prizes"><column name="draw_id" value="113"></column><column name="stars" value="2"></column><column name="numbers" value="4"></column><column name="prize" value="4860.30"></column></insert>
        <insert tableName="draws_prizes"><column name="draw_id" value="113"></column><column name="stars" value="1"></column><column name="numbers" value="4"></column><column name="prize" value="192.10"></column></insert>
        <insert tableName="draws_prizes"><column name="draw_id" value="113"></column><column name="stars" value="0"></column><column name="numbers" value="4"></column><column name="prize" value="90.40"></column></insert>
        <insert tableName="draws_prizes"><column name="draw_id" value="113"></column><column name="stars" value="2"></column><column name="numbers" value="3"></column><column name="prize" value="66.70"></column></insert>
        <insert tableName="draws_prizes"><column name="draw_id" value="113"></column><column name="stars" value="1"></column><column name="numbers" value="3"></column><column name="prize" value="20.50"></column></insert>
        <insert tableName="draws_prizes"><column name="draw_id" value="113"></column><column name="stars" value="2"></column><column name="numbers" value="2"></column><column name="prize" value="19.80"></column></insert>
        <insert tableName="draws_prizes"><column name="draw_id" value="113"></column><column name="stars" value="0"></column><column name="numbers" value="3"></column><column name="prize" value="13.00"></column></insert>
        <insert tableName="draws_prizes"><column name="draw_id" value="113"></column><column name="stars" value="2"></column><column name="numbers" value="1"></column><column name="prize" value="8.70"></column></insert>
        <insert tableName="draws_prizes"><column name="draw_id" value="113"></column><column name="stars" value="1"></column><column name="numbers" value="2"></column><column name="prize" value="6.40"></column></insert>

        <insert tableName="draws"><column name="id" value="114"></column><column name="date" value="2006-04-14"></column><column name="cost" value="1.50"></column><column name="stars_count" value="9"></column><column name="numbers_count" value="50"></column></insert>
        <insert tableName="draws_stars"><column name="draw_id" value="114"></column><column name="star" value="2"></column></insert>
        <insert tableName="draws_stars"><column name="draw_id" value="114"></column><column name="star" value="6"></column></insert>
        <insert tableName="draws_numbers"><column name="draw_id" value="114"></column><column name="number" value="16"></column></insert>
        <insert tableName="draws_numbers"><column name="draw_id" value="114"></column><column name="number" value="26"></column></insert>
        <insert tableName="draws_numbers"><column name="draw_id" value="114"></column><column name="number" value="34"></column></insert>
        <insert tableName="draws_numbers"><column name="draw_id" value="114"></column><column name="number" value="35"></column></insert>
        <insert tableName="draws_numbers"><column name="draw_id" value="114"></column><column name="number" value="49"></column></insert>
        <insert tableName="draws_prizes"><column name="draw_id" value="114"></column><column name="stars" value="2"></column><column name="numbers" value="5"></column><column name="prize" value="17804197.80"></column></insert>
        <insert tableName="draws_prizes"><column name="draw_id" value="114"></column><column name="stars" value="1"></column><column name="numbers" value="5"></column><column name="prize" value="609700.00"></column></insert>
        <insert tableName="draws_prizes"><column name="draw_id" value="114"></column><column name="stars" value="0"></column><column name="numbers" value="5"></column><column name="prize" value="300820.50"></column></insert>
        <insert tableName="draws_prizes"><column name="draw_id" value="114"></column><column name="stars" value="2"></column><column name="numbers" value="4"></column><column name="prize" value="3803.00"></column></insert>
        <insert tableName="draws_prizes"><column name="draw_id" value="114"></column><column name="stars" value="1"></column><column name="numbers" value="4"></column><column name="prize" value="241.50"></column></insert>
        <insert tableName="draws_prizes"><column name="draw_id" value="114"></column><column name="stars" value="0"></column><column name="numbers" value="4"></column><column name="prize" value="116.50"></column></insert>
        <insert tableName="draws_prizes"><column name="draw_id" value="114"></column><column name="stars" value="2"></column><column name="numbers" value="3"></column><column name="prize" value="54.60"></column></insert>
        <insert tableName="draws_prizes"><column name="draw_id" value="114"></column><column name="stars" value="1"></column><column name="numbers" value="3"></column><column name="prize" value="25.70"></column></insert>
        <insert tableName="draws_prizes"><column name="draw_id" value="114"></column><column name="stars" value="2"></column><column name="numbers" value="2"></column><column name="prize" value="17.50"></column></insert>
        <insert tableName="draws_prizes"><column name="draw_id" value="114"></column><column name="stars" value="0"></column><column name="numbers" value="3"></column><column name="prize" value="15.60"></column></insert>
        <insert tableName="draws_prizes"><column name="draw_id" value="114"></column><column name="stars" value="2"></column><column name="numbers" value="1"></column><column name="prize" value="7.40"></column></insert>
        <insert tableName="draws_prizes"><column name="draw_id" value="114"></column><column name="stars" value="1"></column><column name="numbers" value="2"></column><column name="prize" value="8.30"></column></insert>

        <insert tableName="draws"><column name="id" value="115"></column><column name="date" value="2006-04-21"></column><column name="cost" value="1.50"></column><column name="stars_count" value="9"></column><column name="numbers_count" value="50"></column></insert>
        <insert tableName="draws_stars"><column name="draw_id" value="115"></column><column name="star" value="1"></column></insert>
        <insert tableName="draws_stars"><column name="draw_id" value="115"></column><column name="star" value="9"></column></insert>
        <insert tableName="draws_numbers"><column name="draw_id" value="115"></column><column name="number" value="1"></column></insert>
        <insert tableName="draws_numbers"><column name="draw_id" value="115"></column><column name="number" value="20"></column></insert>
        <insert tableName="draws_numbers"><column name="draw_id" value="115"></column><column name="number" value="22"></column></insert>
        <insert tableName="draws_numbers"><column name="draw_id" value="115"></column><column name="number" value="37"></column></insert>
        <insert tableName="draws_numbers"><column name="draw_id" value="115"></column><column name="number" value="46"></column></insert>
        <insert tableName="draws_prizes"><column name="draw_id" value="115"></column><column name="stars" value="2"></column><column name="numbers" value="5"></column><column name="prize" value="10440000.00"></column></insert>
        <insert tableName="draws_prizes"><column name="draw_id" value="115"></column><column name="stars" value="1"></column><column name="numbers" value="5"></column><column name="prize" value="399700.00"></column></insert>
        <insert tableName="draws_prizes"><column name="draw_id" value="115"></column><column name="stars" value="0"></column><column name="numbers" value="5"></column><column name="prize" value="81000.00"></column></insert>
        <insert tableName="draws_prizes"><column name="draw_id" value="115"></column><column name="stars" value="2"></column><column name="numbers" value="4"></column><column name="prize" value="4051.20"></column></insert>
        <insert tableName="draws_prizes"><column name="draw_id" value="115"></column><column name="stars" value="1"></column><column name="numbers" value="4"></column><column name="prize" value="273.60"></column></insert>
        <insert tableName="draws_prizes"><column name="draw_id" value="115"></column><column name="stars" value="0"></column><column name="numbers" value="4"></column><column name="prize" value="130.90"></column></insert>
        <insert tableName="draws_prizes"><column name="draw_id" value="115"></column><column name="stars" value="2"></column><column name="numbers" value="3"></column><column name="prize" value="60.70"></column></insert>
        <insert tableName="draws_prizes"><column name="draw_id" value="115"></column><column name="stars" value="1"></column><column name="numbers" value="3"></column><column name="prize" value="27.80"></column></insert>
        <insert tableName="draws_prizes"><column name="draw_id" value="115"></column><column name="stars" value="2"></column><column name="numbers" value="2"></column><column name="prize" value="17.00"></column></insert>
        <insert tableName="draws_prizes"><column name="draw_id" value="115"></column><column name="stars" value="0"></column><column name="numbers" value="3"></column><column name="prize" value="16.10"></column></insert>
        <insert tableName="draws_prizes"><column name="draw_id" value="115"></column><column name="stars" value="2"></column><column name="numbers" value="1"></column><column name="prize" value="7.30"></column></insert>
        <insert tableName="draws_prizes"><column name="draw_id" value="115"></column><column name="stars" value="1"></column><column name="numbers" value="2"></column><column name="prize" value="8.40"></column></insert>

        <insert tableName="draws"><column name="id" value="116"></column><column name="date" value="2006-04-28"></column><column name="cost" value="1.50"></column><column name="stars_count" value="9"></column><column name="numbers_count" value="50"></column></insert>
        <insert tableName="draws_stars"><column name="draw_id" value="116"></column><column name="star" value="5"></column></insert>
        <insert tableName="draws_stars"><column name="draw_id" value="116"></column><column name="star" value="7"></column></insert>
        <insert tableName="draws_numbers"><column name="draw_id" value="116"></column><column name="number" value="5"></column></insert>
        <insert tableName="draws_numbers"><column name="draw_id" value="116"></column><column name="number" value="10"></column></insert>
        <insert tableName="draws_numbers"><column name="draw_id" value="116"></column><column name="number" value="17"></column></insert>
        <insert tableName="draws_numbers"><column name="draw_id" value="116"></column><column name="number" value="22"></column></insert>
        <insert tableName="draws_numbers"><column name="draw_id" value="116"></column><column name="number" value="33"></column></insert>
        <insert tableName="draws_prizes"><column name="draw_id" value="116"></column><column name="stars" value="2"></column><column name="numbers" value="5"></column><column name="prize" value="17970266.00"></column></insert>
        <insert tableName="draws_prizes"><column name="draw_id" value="116"></column><column name="stars" value="1"></column><column name="numbers" value="5"></column><column name="prize" value="106529.50"></column></insert>
        <insert tableName="draws_prizes"><column name="draw_id" value="116"></column><column name="stars" value="0"></column><column name="numbers" value="5"></column><column name="prize" value="25100.00"></column></insert>
        <insert tableName="draws_prizes"><column name="draw_id" value="116"></column><column name="stars" value="2"></column><column name="numbers" value="4"></column><column name="prize" value="1420.60"></column></insert>
        <insert tableName="draws_prizes"><column name="draw_id" value="116"></column><column name="stars" value="1"></column><column name="numbers" value="4"></column><column name="prize" value="97.60"></column></insert>
        <insert tableName="draws_prizes"><column name="draw_id" value="116"></column><column name="stars" value="0"></column><column name="numbers" value="4"></column><column name="prize" value="58.80"></column></insert>
        <insert tableName="draws_prizes"><column name="draw_id" value="116"></column><column name="stars" value="2"></column><column name="numbers" value="3"></column><column name="prize" value="30.10"></column></insert>
        <insert tableName="draws_prizes"><column name="draw_id" value="116"></column><column name="stars" value="1"></column><column name="numbers" value="3"></column><column name="prize" value="14.80"></column></insert>
        <insert tableName="draws_prizes"><column name="draw_id" value="116"></column><column name="stars" value="2"></column><column name="numbers" value="2"></column><column name="prize" value="11.70"></column></insert>
        <insert tableName="draws_prizes"><column name="draw_id" value="116"></column><column name="stars" value="0"></column><column name="numbers" value="3"></column><column name="prize" value="11.10"></column></insert>
        <insert tableName="draws_prizes"><column name="draw_id" value="116"></column><column name="stars" value="2"></column><column name="numbers" value="1"></column><column name="prize" value="6.10"></column></insert>
        <insert tableName="draws_prizes"><column name="draw_id" value="116"></column><column name="stars" value="1"></column><column name="numbers" value="2"></column><column name="prize" value="5.80"></column></insert>

        <insert tableName="draws"><column name="id" value="117"></column><column name="date" value="2006-05-05"></column><column name="cost" value="1.50"></column><column name="stars_count" value="9"></column><column name="numbers_count" value="50"></column></insert>
        <insert tableName="draws_stars"><column name="draw_id" value="117"></column><column name="star" value="3"></column></insert>
        <insert tableName="draws_stars"><column name="draw_id" value="117"></column><column name="star" value="9"></column></insert>
        <insert tableName="draws_numbers"><column name="draw_id" value="117"></column><column name="number" value="4"></column></insert>
        <insert tableName="draws_numbers"><column name="draw_id" value="117"></column><column name="number" value="8"></column></insert>
        <insert tableName="draws_numbers"><column name="draw_id" value="117"></column><column name="number" value="14"></column></insert>
        <insert tableName="draws_numbers"><column name="draw_id" value="117"></column><column name="number" value="16"></column></insert>
        <insert tableName="draws_numbers"><column name="draw_id" value="117"></column><column name="number" value="50"></column></insert>
        <insert tableName="draws_prizes"><column name="draw_id" value="117"></column><column name="stars" value="2"></column><column name="numbers" value="5"></column><column name="prize" value="10320000.00"></column></insert>
        <insert tableName="draws_prizes"><column name="draw_id" value="117"></column><column name="stars" value="1"></column><column name="numbers" value="5"></column><column name="prize" value="472991.20"></column></insert>
        <insert tableName="draws_prizes"><column name="draw_id" value="117"></column><column name="stars" value="0"></column><column name="numbers" value="5"></column><column name="prize" value="134227.20"></column></insert>
        <insert tableName="draws_prizes"><column name="draw_id" value="117"></column><column name="stars" value="2"></column><column name="numbers" value="4"></column><column name="prize" value="3550.90"></column></insert>
        <insert tableName="draws_prizes"><column name="draw_id" value="117"></column><column name="stars" value="1"></column><column name="numbers" value="4"></column><column name="prize" value="176.60"></column></insert>
        <insert tableName="draws_prizes"><column name="draw_id" value="117"></column><column name="stars" value="0"></column><column name="numbers" value="4"></column><column name="prize" value="78.00"></column></insert>
        <insert tableName="draws_prizes"><column name="draw_id" value="117"></column><column name="stars" value="2"></column><column name="numbers" value="3"></column><column name="prize" value="61.60"></column></insert>
        <insert tableName="draws_prizes"><column name="draw_id" value="117"></column><column name="stars" value="1"></column><column name="numbers" value="3"></column><column name="prize" value="19.70"></column></insert>
        <insert tableName="draws_prizes"><column name="draw_id" value="117"></column><column name="stars" value="2"></column><column name="numbers" value="2"></column><column name="prize" value="19.00"></column></insert>
        <insert tableName="draws_prizes"><column name="draw_id" value="117"></column><column name="stars" value="0"></column><column name="numbers" value="3"></column><column name="prize" value="11.00"></column></insert>
        <insert tableName="draws_prizes"><column name="draw_id" value="117"></column><column name="stars" value="2"></column><column name="numbers" value="1"></column><column name="prize" value="8.40"></column></insert>
        <insert tableName="draws_prizes"><column name="draw_id" value="117"></column><column name="stars" value="1"></column><column name="numbers" value="2"></column><column name="prize" value="6.60"></column></insert>

        <insert tableName="draws"><column name="id" value="118"></column><column name="date" value="2006-05-12"></column><column name="cost" value="1.50"></column><column name="stars_count" value="9"></column><column name="numbers_count" value="50"></column></insert>
        <insert tableName="draws_stars"><column name="draw_id" value="118"></column><column name="star" value="1"></column></insert>
        <insert tableName="draws_stars"><column name="draw_id" value="118"></column><column name="star" value="5"></column></insert>
        <insert tableName="draws_numbers"><column name="draw_id" value="118"></column><column name="number" value="5"></column></insert>
        <insert tableName="draws_numbers"><column name="draw_id" value="118"></column><column name="number" value="20"></column></insert>
        <insert tableName="draws_numbers"><column name="draw_id" value="118"></column><column name="number" value="23"></column></insert>
        <insert tableName="draws_numbers"><column name="draw_id" value="118"></column><column name="number" value="34"></column></insert>
        <insert tableName="draws_numbers"><column name="draw_id" value="118"></column><column name="number" value="50"></column></insert>
        <insert tableName="draws_prizes"><column name="draw_id" value="118"></column><column name="stars" value="2"></column><column name="numbers" value="5"></column><column name="prize" value="17589298.00"></column></insert>
        <insert tableName="draws_prizes"><column name="draw_id" value="118"></column><column name="stars" value="1"></column><column name="numbers" value="5"></column><column name="prize" value="190500.00"></column></insert>
        <insert tableName="draws_prizes"><column name="draw_id" value="118"></column><column name="stars" value="0"></column><column name="numbers" value="5"></column><column name="prize" value="39656.60"></column></insert>
        <insert tableName="draws_prizes"><column name="draw_id" value="118"></column><column name="stars" value="2"></column><column name="numbers" value="4"></column><column name="prize" value="2672.20"></column></insert>
        <insert tableName="draws_prizes"><column name="draw_id" value="118"></column><column name="stars" value="1"></column><column name="numbers" value="4"></column><column name="prize" value="140.00"></column></insert>
        <insert tableName="draws_prizes"><column name="draw_id" value="118"></column><column name="stars" value="0"></column><column name="numbers" value="4"></column><column name="prize" value="77.90"></column></insert>
        <insert tableName="draws_prizes"><column name="draw_id" value="118"></column><column name="stars" value="2"></column><column name="numbers" value="3"></column><column name="prize" value="45.40"></column></insert>
        <insert tableName="draws_prizes"><column name="draw_id" value="118"></column><column name="stars" value="1"></column><column name="numbers" value="3"></column><column name="prize" value="18.60"></column></insert>
        <insert tableName="draws_prizes"><column name="draw_id" value="118"></column><column name="stars" value="2"></column><column name="numbers" value="2"></column><column name="prize" value="15.10"></column></insert>
        <insert tableName="draws_prizes"><column name="draw_id" value="118"></column><column name="stars" value="0"></column><column name="numbers" value="3"></column><column name="prize" value="13.50"></column></insert>
        <insert tableName="draws_prizes"><column name="draw_id" value="118"></column><column name="stars" value="2"></column><column name="numbers" value="1"></column><column name="prize" value="7.30"></column></insert>
        <insert tableName="draws_prizes"><column name="draw_id" value="118"></column><column name="stars" value="1"></column><column name="numbers" value="2"></column><column name="prize" value="6.50"></column></insert>

        <insert tableName="draws"><column name="id" value="119"></column><column name="date" value="2006-05-19"></column><column name="cost" value="1.50"></column><column name="stars_count" value="9"></column><column name="numbers_count" value="50"></column></insert>
        <insert tableName="draws_stars"><column name="draw_id" value="119"></column><column name="star" value="5"></column></insert>
        <insert tableName="draws_stars"><column name="draw_id" value="119"></column><column name="star" value="8"></column></insert>
        <insert tableName="draws_numbers"><column name="draw_id" value="119"></column><column name="number" value="3"></column></insert>
        <insert tableName="draws_numbers"><column name="draw_id" value="119"></column><column name="number" value="5"></column></insert>
        <insert tableName="draws_numbers"><column name="draw_id" value="119"></column><column name="number" value="25"></column></insert>
        <insert tableName="draws_numbers"><column name="draw_id" value="119"></column><column name="number" value="34"></column></insert>
        <insert tableName="draws_numbers"><column name="draw_id" value="119"></column><column name="number" value="49"></column></insert>
        <insert tableName="draws_prizes"><column name="draw_id" value="119"></column><column name="stars" value="2"></column><column name="numbers" value="5"></column><column name="prize" value="10137000.00"></column></insert>
        <insert tableName="draws_prizes"><column name="draw_id" value="119"></column><column name="stars" value="1"></column><column name="numbers" value="5"></column><column name="prize" value="956384.80"></column></insert>
        <insert tableName="draws_prizes"><column name="draw_id" value="119"></column><column name="stars" value="0"></column><column name="numbers" value="5"></column><column name="prize" value="159500.00"></column></insert>
        <insert tableName="draws_prizes"><column name="draw_id" value="119"></column><column name="stars" value="2"></column><column name="numbers" value="4"></column><column name="prize" value="4846.50"></column></insert>
        <insert tableName="draws_prizes"><column name="draw_id" value="119"></column><column name="stars" value="1"></column><column name="numbers" value="4"></column><column name="prize" value="198.50"></column></insert>
        <insert tableName="draws_prizes"><column name="draw_id" value="119"></column><column name="stars" value="0"></column><column name="numbers" value="4"></column><column name="prize" value="108.40"></column></insert>
        <insert tableName="draws_prizes"><column name="draw_id" value="119"></column><column name="stars" value="2"></column><column name="numbers" value="3"></column><column name="prize" value="52.40"></column></insert>
        <insert tableName="draws_prizes"><column name="draw_id" value="119"></column><column name="stars" value="1"></column><column name="numbers" value="3"></column><column name="prize" value="20.70"></column></insert>
        <insert tableName="draws_prizes"><column name="draw_id" value="119"></column><column name="stars" value="2"></column><column name="numbers" value="2"></column><column name="prize" value="14.80"></column></insert>
        <insert tableName="draws_prizes"><column name="draw_id" value="119"></column><column name="stars" value="0"></column><column name="numbers" value="3"></column><column name="prize" value="14.20"></column></insert>
        <insert tableName="draws_prizes"><column name="draw_id" value="119"></column><column name="stars" value="2"></column><column name="numbers" value="1"></column><column name="prize" value="6.50"></column></insert>
        <insert tableName="draws_prizes"><column name="draw_id" value="119"></column><column name="stars" value="1"></column><column name="numbers" value="2"></column><column name="prize" value="6.50"></column></insert>

        <insert tableName="draws"><column name="id" value="120"></column><column name="date" value="2006-05-26"></column><column name="cost" value="1.50"></column><column name="stars_count" value="9"></column><column name="numbers_count" value="50"></column></insert>
        <insert tableName="draws_stars"><column name="draw_id" value="120"></column><column name="star" value="3"></column></insert>
        <insert tableName="draws_stars"><column name="draw_id" value="120"></column><column name="star" value="7"></column></insert>
        <insert tableName="draws_numbers"><column name="draw_id" value="120"></column><column name="number" value="2"></column></insert>
        <insert tableName="draws_numbers"><column name="draw_id" value="120"></column><column name="number" value="12"></column></insert>
        <insert tableName="draws_numbers"><column name="draw_id" value="120"></column><column name="number" value="21"></column></insert>
        <insert tableName="draws_numbers"><column name="draw_id" value="120"></column><column name="number" value="41"></column></insert>
        <insert tableName="draws_numbers"><column name="draw_id" value="120"></column><column name="number" value="49"></column></insert>
        <insert tableName="draws_prizes"><column name="draw_id" value="120"></column><column name="stars" value="2"></column><column name="numbers" value="5"></column><column name="prize" value="5163000.00"></column></insert>
        <insert tableName="draws_prizes"><column name="draw_id" value="120"></column><column name="stars" value="1"></column><column name="numbers" value="5"></column><column name="prize" value="208484.20"></column></insert>
        <insert tableName="draws_prizes"><column name="draw_id" value="120"></column><column name="stars" value="0"></column><column name="numbers" value="5"></column><column name="prize" value="31322.30"></column></insert>
        <insert tableName="draws_prizes"><column name="draw_id" value="120"></column><column name="stars" value="2"></column><column name="numbers" value="4"></column><column name="prize" value="3169.50"></column></insert>
        <insert tableName="draws_prizes"><column name="draw_id" value="120"></column><column name="stars" value="1"></column><column name="numbers" value="4"></column><column name="prize" value="199.90"></column></insert>
        <insert tableName="draws_prizes"><column name="draw_id" value="120"></column><column name="stars" value="0"></column><column name="numbers" value="4"></column><column name="prize" value="86.90"></column></insert>
        <insert tableName="draws_prizes"><column name="draw_id" value="120"></column><column name="stars" value="2"></column><column name="numbers" value="3"></column><column name="prize" value="44.80"></column></insert>
        <insert tableName="draws_prizes"><column name="draw_id" value="120"></column><column name="stars" value="1"></column><column name="numbers" value="3"></column><column name="prize" value="24.20"></column></insert>
        <insert tableName="draws_prizes"><column name="draw_id" value="120"></column><column name="stars" value="2"></column><column name="numbers" value="2"></column><column name="prize" value="13.20"></column></insert>
        <insert tableName="draws_prizes"><column name="draw_id" value="120"></column><column name="stars" value="0"></column><column name="numbers" value="3"></column><column name="prize" value="14.20"></column></insert>
        <insert tableName="draws_prizes"><column name="draw_id" value="120"></column><column name="stars" value="2"></column><column name="numbers" value="1"></column><column name="prize" value="5.60"></column></insert>
        <insert tableName="draws_prizes"><column name="draw_id" value="120"></column><column name="stars" value="1"></column><column name="numbers" value="2"></column><column name="prize" value="7.50"></column></insert>

    </changeSet>
</databaseChangeLog>